keystorage/__init__.py
keystorage/aes.py
keystorage/db.py
keystorage/schema.py
keystorage/scripts.py
keystorage/tesqlite.py
keystorage/testencript.py
keystorage-0.2.1.dist-info/LICENSE.md
keystorage-0.2.1.dist-info/METADATA
keystorage-0.2.1.dist-info/WHEEL
keystorage-0.2.1.dist-info/entry_points.txt
keystorage-0.2.1.dist-info/top_level.txt
keystorage-0.2.1.dist-info/RECORD
