Metadata-Version: 2.1
Name: keystorage
Version: 0.2.1
Summary: a simple program to manage passwords
Home-page: https://github.com/fraco-oxza/keyStorage
Author: Francisco Carvajal Ossa
Author-email: fraco_oxza@outlook.com
License: MIT license
Platform: Linux
Requires-Python: >=3.6
Requires-Dist: click
Requires-Dist: pycrypto
